turbobatch.py
turbobatch-1.0.0.dist-info/licenses/LICENSE
turbobatch-1.0.0.dist-info/METADATA
turbobatch-1.0.0.dist-info/WHEEL
turbobatch-1.0.0.dist-info/top_level.txt
turbobatch-1.0.0.dist-info/RECORD
