Metadata-Version: 2.4
Name: turbobatch
Version: 1.0.0
Summary: 🚀 High-Performance Dynamic Batching for Transformer Models
Home-page: https://github.com/Shayanthn/turbobatch
Author: Shayan Taherkhani
Author-email: shayan.taherkhani@studio.unibo.it
Project-URL: Bug Reports, https://github.com/Shayanthn/turbobatch/issues
Project-URL: Source, https://github.com/Shayanthn/turbobatch
Project-URL: Documentation, https://github.com/Shayanthn/turbobatch#readme
Project-URL: Personal Website, https://shayantaherkhani.ir
Keywords: transformers,batching,inference,optimization,pytorch,huggingface
Classifier: Development Status :: 5 - Production/Stable
Classifier: Intended Audience :: Developers
Classifier: Intended Audience :: Science/Research
Classifier: License :: OSI Approved :: MIT License
Classifier: Operating System :: OS Independent
Classifier: Programming Language :: Python :: 3
Classifier: Programming Language :: Python :: 3.8
Classifier: Programming Language :: Python :: 3.9
Classifier: Programming Language :: Python :: 3.10
Classifier: Programming Language :: Python :: 3.11
Classifier: Topic :: Scientific/Engineering :: Artificial Intelligence
Classifier: Topic :: Software Development :: Libraries :: Python Modules
Requires-Python: >=3.8
License-File: LICENSE
Requires-Dist: torch>=1.9.0
Requires-Dist: transformers>=4.20.0
Requires-Dist: numpy>=1.21.0
Provides-Extra: dev
Requires-Dist: pytest>=7.0.0; extra == "dev"
Requires-Dist: black>=22.0.0; extra == "dev"
Requires-Dist: isort>=5.10.0; extra == "dev"
Requires-Dist: mypy>=0.991; extra == "dev"
Provides-Extra: monitoring
Requires-Dist: psutil>=5.9.0; extra == "monitoring"
Requires-Dist: GPUtil>=1.4.0; extra == "monitoring"
Provides-Extra: examples
Requires-Dist: tqdm>=4.64.0; extra == "examples"
Requires-Dist: matplotlib>=3.5.0; extra == "examples"
Requires-Dist: seaborn>=0.11.0; extra == "examples"
Requires-Dist: jupyter>=1.0.0; extra == "examples"
Requires-Dist: datasets>=2.0.0; extra == "examples"
Provides-Extra: acceleration
Requires-Dist: accelerate>=0.20.0; extra == "acceleration"
Provides-Extra: all
Requires-Dist: pytest>=7.0.0; extra == "all"
Requires-Dist: black>=22.0.0; extra == "all"
Requires-Dist: isort>=5.10.0; extra == "all"
Requires-Dist: mypy>=0.991; extra == "all"
Requires-Dist: psutil>=5.9.0; extra == "all"
Requires-Dist: GPUtil>=1.4.0; extra == "all"
Requires-Dist: tqdm>=4.64.0; extra == "all"
Requires-Dist: matplotlib>=3.5.0; extra == "all"
Requires-Dist: seaborn>=0.11.0; extra == "all"
Requires-Dist: jupyter>=1.0.0; extra == "all"
Requires-Dist: datasets>=2.0.0; extra == "all"
Requires-Dist: accelerate>=0.20.0; extra == "all"
Dynamic: author
Dynamic: author-email
Dynamic: classifier
Dynamic: description
Dynamic: description-content-type
Dynamic: home-page
Dynamic: keywords
Dynamic: license-file
Dynamic: project-url
Dynamic: provides-extra
Dynamic: requires-dist
Dynamic: requires-python
Dynamic: summary
